algorithm.py
algorithm-1.2.0.dist-info/DESCRIPTION.rst
algorithm-1.2.0.dist-info/METADATA
algorithm-1.2.0.dist-info/RECORD
algorithm-1.2.0.dist-info/WHEEL
algorithm-1.2.0.dist-info/metadata.json
algorithm-1.2.0.dist-info/top_level.txt
